ltdconveyor/__init__.py
ltdconveyor/exceptions.py
ltdconveyor/fastly.py
ltdconveyor/testutils.py
ltdconveyor/cli/__init__.py
ltdconveyor/cli/main.py
ltdconveyor/cli/upload.py
ltdconveyor/cli/utils.py
ltdconveyor/keeper/__init__.py
ltdconveyor/keeper/build.py
ltdconveyor/keeper/exceptions.py
ltdconveyor/keeper/login.py
ltdconveyor/s3/__init__.py
ltdconveyor/s3/copy.py
ltdconveyor/s3/delete.py
ltdconveyor/s3/exceptions.py
ltdconveyor/s3/presignedpost.py
ltdconveyor/s3/upload.py
ltdconveyor/s3/utils.py
ltd_conveyor-0.8.4.dist-info/LICENSE
ltd_conveyor-0.8.4.dist-info/METADATA
ltd_conveyor-0.8.4.dist-info/WHEEL
ltd_conveyor-0.8.4.dist-info/entry_points.txt
ltd_conveyor-0.8.4.dist-info/top_level.txt
ltd_conveyor-0.8.4.dist-info/RECORD
