Metadata-Version: 2.1
Name: ltd-conveyor
Version: 0.8.4
Summary: LSST the Docs admin client.
Home-page: https://ltd-conveyor.lsst.io
Author: Association of Universities for Research in Astronomy, Inc. (AURA)
Author-email: sqre-admin@lists.lsst.org
License: MIT
Project-URL: Change log, https://ltd-conveyor.lsst.io/changes.html
Project-URL: Source code, https://github.com/lsst-sqre/ltd-conveyor
Project-URL: Issue tracker, https://github.com/lsst-sqre/ltd-conveyor/issues
Keywords: lsst
Classifier: Development Status :: 4 - Beta
Classifier: License :: OSI Approved :: MIT License
Classifier: Programming Language :: Python
Classifier: Programming Language :: Python :: 3
Classifier: Programming Language :: Python :: 3.7
Classifier: Programming Language :: Python :: 3.8
Classifier: Programming Language :: Python :: 3.9
Classifier: Intended Audience :: Developers
Classifier: Environment :: Console
Classifier: Natural Language :: English
Classifier: Operating System :: POSIX
Requires-Python: >=3.7
License-File: LICENSE
Requires-Dist: boto3
Requires-Dist: requests
Requires-Dist: uritemplate
Requires-Dist: click
Requires-Dist: importlib-metadata
Provides-Extra: dev
Requires-Dist: responses; extra == "dev"
Requires-Dist: pytest; extra == "dev"
Requires-Dist: pytest-mock; extra == "dev"
Requires-Dist: documenteer[pipelines]; extra == "dev"
Requires-Dist: sphinx-click; extra == "dev"
Requires-Dist: coverage[toml]; extra == "dev"
Requires-Dist: Sphinx; extra == "dev"
Requires-Dist: mypy; extra == "dev"
Requires-Dist: types-requests; extra == "dev"
Requires-Dist: types-setuptools; extra == "dev"
